rst2twiki.py
rst2wiki.py
setup.py
rst2twiki.egg-info/PKG-INFO
rst2twiki.egg-info/SOURCES.txt
rst2twiki.egg-info/dependency_links.txt
rst2twiki.egg-info/top_level.txt