Metadata-Version: 1.0
Name: rst2twiki
Version: 0.1
Summary: reStructuredText to twiki
Home-page: https://github.com/idning/rst2twiki
Author: ning
Author-email: idning@gmail.com
License: UNKNOWN
Platform: UNKNOWN
Classifier: Development Status :: 5 - Production/Stable
Classifier: Environment :: Console
Classifier: License :: OSI Approved :: GNU Affero General Public License v3
Classifier: Operating System :: OS Independent
Classifier: Programming Language :: Python
Classifier: Topic :: Internet :: WWW/HTTP
Classifier: Topic :: Software Development :: Libraries :: Python Modules
